wcpan/drive/sqlite/__init__.py
wcpan/drive/sqlite/_inner.py
wcpan/drive/sqlite/_lib.py
wcpan/drive/sqlite/_outer.py
wcpan/drive/sqlite/_service.py
wcpan/drive/sqlite/_sql.py
wcpan/drive/sqlite/exceptions.py
wcpan/drive/sqlite/lib.py
wcpan/drive/sqlite/py.typed
wcpan_drive_sqlite-2.1.0.dist-info/LICENSE.txt
wcpan_drive_sqlite-2.1.0.dist-info/METADATA
wcpan_drive_sqlite-2.1.0.dist-info/WHEEL
wcpan_drive_sqlite-2.1.0.dist-info/RECORD
