Metadata-Version: 2.1
Name: wcpan-drive-sqlite
Version: 2.1.0
Summary: sqlite3 snapshot service for wcpan.drive
Home-page: https://github.com/legnaleurc/wcpan.drive.sqlite
License: MIT
Author: Wei-Cheng Pan
Author-email: legnaleurc@gmail.com
Requires-Python: >=3.12,<4.0
Classifier: Development Status :: 3 - Alpha
Classifier: Intended Audience :: Developers
Classifier: License :: OSI Approved :: MIT License
Classifier: Operating System :: OS Independent
Classifier: Programming Language :: Python :: 3
Classifier: Programming Language :: Python :: 3.12
Classifier: Topic :: Software Development :: Libraries
Classifier: Typing :: Typed
Requires-Dist: wcpan-drive-core (>=4.1.0,<5.0.0)
Project-URL: Repository, https://github.com/legnaleurc/wcpan.drive.sqlite
